LICENSE
README.rst
pyproject.toml
setup.cfg
setup.py
django_informixdb_vault/__init__.py
django_informixdb_vault/base.py
django_informixdb_vault/version.py
django_informixdb_vault.egg-info/PKG-INFO
django_informixdb_vault.egg-info/SOURCES.txt
django_informixdb_vault.egg-info/dependency_links.txt
django_informixdb_vault.egg-info/requires.txt
django_informixdb_vault.egg-info/top_level.txt
test/test_base.py