Metadata-Version: 2.1
Name: django-informixdb-vault
Version: 0.6.3
Summary: A database driver for Django to connect to an Informix db via ODBC, obtaining the credentials from Hashicorp Vault
Author-email: Reecetech <opensource@reecetech.com.au>
License: APLv2
Project-URL: Homepage, https://github.com/reecetech/django_informixdb_vault
Project-URL: Repository, https://github.com/reecetech/django_informixdb_vault
Keywords: django,informix,vault
Classifier: Development Status :: 4 - Beta
Classifier: Intended Audience :: Developers
Classifier: Topic :: Software Development
Classifier: Topic :: Scientific/Engineering
Classifier: License :: OSI Approved :: Apache Software License
Classifier: Programming Language :: Python :: 3
Classifier: Programming Language :: Python :: 3.9
Classifier: Programming Language :: Python :: 3.10
License-File: LICENSE
